.gitignore
AUTHORS.rst
CHANGELOG.rst
LICENSE
README.rst
requirements.txt
setup.cfg
setup.py
docs/Makefile
docs/authors.rst
docs/changelog.rst
docs/conf.py
docs/index.rst
docs/license.rst
docs/_static/.gitignore
src/hypothesis_csv/__init__.py
src/hypothesis_csv/_csv.py
src/hypothesis_csv/_data_rows.py
src/hypothesis_csv/strategies.py
src/hypothesis_csv/type_utils.py
src/hypothesis_csv.egg-info/PKG-INFO
src/hypothesis_csv.egg-info/SOURCES.txt
src/hypothesis_csv.egg-info/dependency_links.txt
src/hypothesis_csv.egg-info/entry_points.txt
src/hypothesis_csv.egg-info/not-zip-safe
src/hypothesis_csv.egg-info/requires.txt
src/hypothesis_csv.egg-info/top_level.txt
tests/conftest.py
tests/test_strategies.py