Metadata-Version: 2.1
Name: hypothesis-csv
Version: 0.3.4
Summary: CSV extension for the Hypothesis framework
Home-page: https://github.com/chobeat/hypothesis-csv
Author: Simone Robutti
Author-email: simone.robutti@teraki.com
License: Apache License
Platform: any
Classifier: Development Status :: 4 - Beta
Classifier: Programming Language :: Python
Classifier: Framework :: Hypothesis
